{
  "images": [
    "https://play-lh.googleusercontent.com/YnXIqDcGY6FYQdCapeMfd79aIr_HV9_gsxg2sGBSEwsDBdXNEA7MDEwjqZywYB2xoQ=w526-h296-rw",
    "https://play-lh.googleusercontent.com/oswGwTHFUw7LJiCLrJHVWiG5n0SyrKgHWxQs9pVXmKOjULuhdfLwCLmu2ydDND9ISgw4=w526-h296-rw",
    "https://play-lh.googleusercontent.com/7d_HD2-tAxQNRprVQGNYpQFyt3xRBGv1e-6cSwevEtHRZrFVYf2oNyGiQWwWjdT7eA=w526-h296-rw",
    "https://play-lh.googleusercontent.com/UoefZFxGTkDg2X09-U4xZR469cA_OszFxe5nftmjM19y-vbQ3BQXcDmuL4uBr4kniA=w526-h296-rw",
    "https://play-lh.googleusercontent.com/57QmO2DeE9D2y0WUASv1-Ogty7GSvWZahp3mFoU4s6AvzWRwF3bhkTS7j74NiQRgkhK-=w526-h296-rw"
  ],
  "title": "Life Makeover",
  "icon": "https://play-lh.googleusercontent.com/aE2tu6k6f4JGjeSb8miztpzoJEoZLkG9XczqxIv4Hkp859MBrsFt5ZOLIWG6Utky4xA=w240-h480-rw",
  "subTitle": "Симулационни/Начин на живот/Обличане на специални дрехи/Казуални",
  "desc": "Версията за сътрудничество Life Makeover x Cardcaptor Sakura е достъпна!<br>1. От 29 октомври до 18 ноември, новата и лимитирана версия на Life Makeover x Cardcaptor Sakura Lightchase [Card Pact] предлага нови 5-звездни комплекти [Clear Prelude] и [Seal Release], както и SR Ally!<br>5-звезден комплект: Clear Prelude<br>Томойо проектира и изработи този костюм с надеждата да види Сакура пред камерата, носеща го.<br>5-звезден комплект: Seal Release<br>Червен костюм, проектиран от Томойо, сладък и оживен, но практичен за действие.<br>2. Unsealing Key Value Pack, който се появява за Card Pact!<br>3. Бонус за влизане: Card Encounter. Влезте за Unsealing Key x15, 4-звездна мода [Frozen Glow] и общо 130 диаманта!<br>4. Ново събитие [Popping Gifts]: Присъединете се към комплекта за сътрудничество Life Makeover x Cardcaptor Sakura!<br>5. Хелоуин лакомство. Влезте за празнични подаръци!<br>6. Нови събития [Проект за вкус], [Супер панаир], [Океански съкровища], [Грижа за растенията] и [Аромат на билки] на път с много 5-звездни и 4-звездни комплекти!<br>7. От 7 до 27 ноември, 6-звезден комплект и съюзник SSR ще се включат в Lightchase [Landscape Thread!]<br>8. От 12 ноември до 2 декември, 5-звездни комплекти и съюзник SR ще се включат в Lightchase [Розова фантазия]!<br>9. Няколко рецепти за Хелоуин с ограничено време за закупуване.<br>10. Колекция с вход за изработка - Специален празник<br>11. Закупете бонус [Сладко пръщене], пакет за външен вид [Звездна земя на мечтите], пакет за външен вид [Ярка концентрация], пакет [Приспивна песен на пълзящо животно] и популярен пакет за външен вид ще се включат скоро.<br>Блясък на различни платформи<br>—Всеки детайл от красотата заслужава внимателно оценяване.<br>Изживейте безпроблемен геймплей на различни платформи със зашеметяваща 4K графика, от рендиране на коса и платове до реалистична метеорологична система. Поканете най-добрите си приятели да взаимодействат във вашето персонализирано убежище!<br>Персонализиране на герои от следващо поколение<br>—127 нови опции за персонализиране на лицето, за да подобрите красотата си.<br>Изваяйте перфектния външен вид от челото до брадичката, от веждите до устните. Фино настройте детайлите в по-голям и по-свободен диапазон. Мечтаното ви лице е само на едно докосване разстояние!<br>Безкрайна палитра, вашият дигитален гардероб<br>—Отключете „безкрайността“ за вашия дигитален гардероб и RBG палитра.<br>От рокли до дантелени облицовки, цветови и стилни модни решения от 3-звездно до 6-звездно ниво. Отключете спиращи дъха ефекти за промяна на цветовете с X Palette и X Starlight!<br>Създайте своя собствена мода<br>—Станете главен дизайнер на собственото си студио.<br>Избирайте платове, коригирайте кройки и създавайте ексклузивни принтове. Превърнете дизайните си от скица в реалност, готова за подиум.<br>Подобрено фотосесийно изживяване<br>Уловете стила си с нашата подобрена фото система. Насладете се на свободно движение на камерата, усъвършенствани инструменти за редактиране и покажете красотата си с всякаква форма на композиция.<br>Home Build 2.0: Разширено и Освободено<br>—Разширен режим на изграждане и строителни блокове.<br>Изградете пространството на мечтите си с нашата система за разположение без мрежа. Подреждайте мебели, регулирайте височините и завъртайте предметите по желание. Плюс това, използвайте нашите нови строителни блокове със 144 цветови опции за фантастични структури!<br>Реалистични домашни любимци<br>Потопете се в ултрареалистични взаимодействия с домашни любимци. Усетете мекотата на козината на котенце или се вгледайте в проникновените очи на кученце. Уловете сладостта от първа ръка и без филтър! Нашата изключително безплатна система за персонализиране на домашни любимци и генетична система, управлявана от изкуствен интелект, гарантират, че всеки домашен любимец е уникален ваш.<br>Съберете всички любители на свободата<br>Споделяйте, вдъхновявайте и се свързвайте в общността Vvanna. Организирайте виртуални събирания, за да се видите с отдавна липсващите си приятели. Посещавайте се, гответе, декорирайте стаи и запазвайте спомени в груповите си снимки.<br>Място с безкрайни възможности за всяко момиче, Life Makeover подкрепя всяка мечта и разпалва всеки потенциал!<br>Официален Instagram: https://www.instagram.com/lifemakeover_global/<br>Официален TikTok: www.tiktok.com/@lifemakeoverofficialOfficial<br>Официален X: https://x.com/LifeMakeover510<br>За да осигурите плавно игрово изживяване, моля, уверете се, че устройството ви отговаря на следните минимални изисквания на играта:<br>Android устройства: Snapdragon 660, Kirin710 или по-нова версия;<br>Минимална оставаща памет: 4GB или по-нова версия;<br>Поддържана система: Android 7.0 или по-нова версия. (Настройки > За телефона > Модел)"
}