{
  "images": [
    "https://play-lh.googleusercontent.com/ddnZyINVQ5pOlJ63AULv1GZfnBFUSSAm2_UaFQ5HizLJcSppKp7zy80KQoeNLzgvh5M=w526-h296-rw",
    "https://play-lh.googleusercontent.com/HXvF5XJ6XF6vvCFPwzW8qCHAWDXc_lwuMiGNwUC5EYrgdkWrr39ifXCgG9v3LMfoTA8=w526-h296-rw",
    "https://play-lh.googleusercontent.com/zTG283-Q0h5u9UEVMEmQbqIGFjYt-E7y2LI0p6lCSD5RwXDlhKP0v7fEfRAw50ESc1A=w526-h296-rw",
    "https://play-lh.googleusercontent.com/L-bM4_9Il3ANLWCiQNx7mLUeQESYPsO0mzLDwLH1s3E4n8VtB6zxNOwZ2M8jgohU7Q=w526-h296-rw",
    "https://play-lh.googleusercontent.com/HEz8XoPNzVDmV_dBdM9Hp748SqOgCXSXyQBHInqYPBBfhbbL-y2uyR-UT-6uMUdbDA=w526-h296-rw"
  ],
  "title": "Block Blast!",
  "icon": "https://play-lh.googleusercontent.com/R0qgNDYYHbRhw6JFsdEbDMqONplEvJx0m0W9wzYVvY3eNF1c2rfBWYjQxW0sLEzFe1E=w240-h480-rw",
  "subTitle": "Пъзели/Блокчета/Казуални",
  "desc": "Влезте в света на Block Blast, забавна и безплатна блокова пъзел игра, където всяко движение предизвиква вашия мозък и стратегия, като ви възнаграждава със задоволителни ефекти на смачкване, докато взривявате кубчета. Независимо дали търсите офлайн релаксация или искате да подобрите логическите си умения, Block Blast предоставя увлекателно изживяване с пъзел.<br>???? Защо ще харесате Block Blast<br>???? Живо приключение с пъзели: Свържете цветни блокове на дъска 8x8, решавайте логически пъзели и гледайте как кубчетата се раздробяват в каскада от цветове.<br>???? Стратегически комбинации и ивици: <br>Използвайте мозъка си, за да изчистите няколко реда блокове с едно движение за мощни комбинации. Поддържайте своите серии, за да постигнете огромни резултати!<br>???? Небрежно, но предизвикателно: Играйте със собствено темпо, отпуснете мозъка си или приложете дълбоки логически стратегии, за да победите най-високия си резултат.<br>???? Забавление офлайн, не е необходим WiFi: Насладете се на безплатна игра с блок пъзел по всяко време и навсякъде, идеална за безкрайно забавление в движение.<br>???? Характеристики на Block Blast<br>● Пъзел игра: Стратегически поставяйте блокове и кубчета, съпоставяйте цветовете и решавайте всяко предизвикателно ниво.<br>● Приключенски режим: Поемете прогресивно предизвикателни пъзели, всяко ниво с уникална тема и визуални стилове.<br>● Ежедневни предизвикателства: Поддържайте мозъка си остър с ежедневни логически пъзели и печелете изключителни постижения.<br>● Оптимизиран за всички устройства: Гладко, безпроблемно игрово изживяване с минимално използване на паметта—идеално за телефони и таблети.<br>???? Как се играе<br>● Drag & Match: Стратегически поставете кубчета върху дъската 8x8.<br>● Crush & Score: Попълнете редове или колони, за да разбивате блокове и да печелите точки.<br>● Комбинации за преследване: Планирайте ходовете си и задействайте масивни комбинации за бонус точки.<br>● Останете стратегически: Приложете логика и стратегия, за да предотвратите запълването на дъската ви.<br>✨ Професионални съвети за майстори на пъзели<br>● Планирайте предварително: Визуализирайте ходовете си, за да държите дъската отворена за по-големи кубчета.<br>● Увеличаване на комбинациите: съпоставете няколко реда и блокове едновременно, за да увеличите своите комбинации.<br>● Овладейте серията: Постоянните изчиствания ще поддържат забавните ви поредици и ще подобрят наградите ви за резултат.<br>???? Влезте в безплатната пъзел игра с блокове!<br>Готови ли сте да тествате мозъка си, да изострите логиката си и да се насладите на часове офлайн забавление с пъзели? Изтеглете Block Blast сега и се впуснете в едно незабравимо приключение с блок пъзел."
}