{
  "images": [
    "https://play-lh.googleusercontent.com/d6rUKu2X0c5gwIgda_vSmO9FsOsAHQL4VYN9FeaALGHtB2JrUJjEYTnJfSC0awH9lA=w526-h296-rw",
    "https://play-lh.googleusercontent.com/egeqNiaGVlGmZO4BNh6sX3v6lsHgFdJAtHCTAmbSbyyfNgQ7onKIMG80_HcO_0Gtfto=w526-h296-rw",
    "https://play-lh.googleusercontent.com/pV1PwKWCFcR0hj_4RLUwjb0ngO8NX6Kt3HIzOGUuvjuzeTdqNUuEW_rFcsKo9Tu1NJ8=w526-h296-rw",
    "https://play-lh.googleusercontent.com/GjkoRrOU281YA1c7ajmrl6CkBOoyIgM4f9fKWgdhZwksIr82hchi2Xx3nUrwPSoTEdCo=w526-h296-rw",
    "https://play-lh.googleusercontent.com/5uuTmi3QkQ15mIjMJFIAlu5YwoTl77kTmRXQYcRHRIdjm2XHZPn3JwfHxezY48iQK3U=w526-h296-rw"
  ],
  "title": "ONE PIECE Bounty Rush",
  "icon": "https://play-lh.googleusercontent.com/MJKv58LUS8uuQ8DXxT0__CZoexpnBz-iRzdQP2SO4oOsP1nYjO8Dsi9-tuuPdCFjXg0V2OxTyy7Axewq2qyRrA=w240-h480-rw",
  "subTitle": "アクション/格闘",
  "desc": "海賊よ、財宝を手に入れろ！ワンピース バウンティラッシュは、人気漫画『ワンピース』の海賊世界を舞台にした3Dアニメバトルアリーナの宝探しゲームです。ルフィ、かの麦わらの一味、そしてお気に入りのキャラクターたちと共に、4対4のリアルタイムPvPバトルでベリーコインの宝を奪い、勝利を掴め！<br>4対4マルチプレイヤー宝探しアクション<br>• エキサイティングなキャプチャー・ザ・フラッグ風アニメ海賊アクション<br>• 4人1チーム2チームがリアルタイムで戦い、より多くの宝を奪い合おう<br>• ベリーコインを奪い合い、勝利を掴め<br>最強の海賊団を結成せよ<br>• ルフィからゾロまで、人気アニメキャラクターを使ってライバルチームと対戦<br>• キャラクターを組み合わせて最強の宝探しチームを結成せよ！<br>• バトル中にキャラクターのかけらを集めて、より多くのキャラクターをアンロックしよう！<br>深海を舞台にしたゲームプレイとレベルアップシステム<br>• キャラクターのクラス選択（アタッカー、ディフェンダー、ランナー）を戦略的に行い、より多くの宝物を集めよう<br>• リーグ戦とソロバトルでキャラクターのグレードとスキルをアップグレード<br>• メダルを装備して、戦闘を有利に展開する特性を付与しよう！<br>ワンピースの世界観を体感せよ<br>• 漫画の世界観が、美しい3Dで再現された戦場<br>• 海辺のレストラン「バラティエ」や砂漠の王国「アラバスタ」など、アニメに登場する象徴的なロケーションでバトルを繰り広げよう。<br>• 各マッチには、チームを優位に導くワンピースの世界観を象徴するアイテムが登場。<br>海賊の皆さん、宝探しの準備はできていますか？仲間を集めて、「ワンピース バウンティラッシュ」で海賊王を目指しましょう！<br>サポート:<br>http://bnfaq.channel.or.jp/contact/faq_list/1908<br>株式会社バンダイナムコエンターテインメント ウェブサイト:<br>https://bandainamcoent.co.jp/english/<br>本アプリをダウンロードまたはインストールすることにより、バンダイナムコエンターテインメントの利用規約に同意したことになります。<br>利用規約:<br>https://legal.bandainamcoent.co.jp/terms/<br>プライバシーポリシー:<br>https://legal.bandainamcoent.co.jp/privacy/<br>ご注意:<br>本ゲームには、ゲームプレイを強化したり、ゲームの進行をスピードアップさせたりするためのアプリ内購入アイテムが含まれています。アプリ内購入はデバイスの設定で無効にすることができます。詳しくは、<br>https://support.google.com/googleplay/answer/1626831?hl=en をご覧ください。<br>©尾田栄一郎／集英社・東映アニメーション<br>©バンダイナムコエンターテインメント<br>本アプリケーションは、ライセンス所有者からの正式な権利に基づいて配信されています。"
}