{
  "images": [
    "https://play-lh.googleusercontent.com/daMPsiomlHjaJ0EBTciR3KuZskFtMsDNGwDPMvR6VL9VTxN2mzmELNFmaUCkSjqKhL0=w526-h296-rw",
    "https://play-lh.googleusercontent.com/vsnW6dmBS25GM52WVrw-ItF7wOCcpxfPHeydKkhJZyMp4eWpSwHb_g4q5JWp_BaXkt0=w526-h296-rw",
    "https://play-lh.googleusercontent.com/9ph6kS0W6Lk73iQq7x8xLSb_ZUwQ_t5wW5hytzy8SDPLTNyo5SZ6pffi1vIvc4ZeUVQ=w526-h296-rw",
    "https://play-lh.googleusercontent.com/1WwOW2BOqAEkikUiWjRjwVTXmOYiXC8UP3t68xH7GrTPMSAI0bzWQJZfWidAZVvTdhs=w526-h296-rw",
    "https://play-lh.googleusercontent.com/Tt1BANRx-6B2eDYdSkA2JuWpEeT-pGr16Tv2W--MCOrTqc0J1paEyBwDGQKuB52ZBiQ=w526-h296-rw"
  ],
  "title": "Squad Busters",
  "icon": "https://play-lh.googleusercontent.com/aSVc4PY9GFLOZDo7hyWOoOSbdS40Oracr-ok21tvk4jyugeXne5ZdMU_GcseUF12vqQ=w240-h480-rw",
  "subTitle": "Aksi/Game IO/Kasual",
  "desc": "Pertarungan menantimu! Pilih Pahlawan & kekuatan spesial Skuad kamu. Taktik dan kemampuanmu menentukan pemenangnya. Semoga beruntung, hanya skuad terbaik yang bertahan sampai akhir!<br>Dalam skuad multipemain, kemenangan ditentukan oleh formasi tepat untuk melancarkan serangan dan melindungi Pahlawan kamu. Mau jadi penembak jitu atau menyerang dan menghancurkan? Koleksi & kembangkan Pahlawan, serta ciptakan Skuad yang sempurna!<br>KOLEKSI & KEMBANGKAN LEBIH DARI 25 KARAKTER<br>Buat kombinasi sempurna untuk setiap pertarungan spesial - koleksi & tingkatkan level karakter unggulan Supercell dengan kemampuan unik mereka yang berasal dari Clash of Clans, Brawl Stars, Hay Day, Clash Royale, dan Boom Beach.<br>MODE SERU & MODIFIKASI<br>Dari Kekacauan multipemain hingga Liga Skuad, perburuan Permata, dan DUO - kamu akan menemukan banyak taktik baru dan kejutan seru dalam setiap permainan! Kejar Goblin Perampas, hancurkan Pinata, dan rekrut Hantu Bangsawan untuk menghantui lawan, dan masih banyak lagi!<br>AKSI, STRATEGI, PERTARUNGAN SERU<br>Lari! Bertarung! Lempar bom BESAR! Berpikir cepat sambil pilih paduan tepat antara taktik menyerang dan melindungi Skuad kamu. Panggil pasukan FUSION raksasa! Bermain aman di luar pertempuran atau pertaruhkan semuanya untuk mengalahkan pemain lain. Ada banyak jalan menuju kemenangan!<br>DUNIA SERU & KARAKTER FAVORIT<br>Bertualang dalam Dunia baru yang seru dengan Peta tematik di perjalananmu. Temukan lingkungan, bos, dan jebakan unik. Semakin tinggi levelmu, semakin banyak karakter pahlawan & penjahat favorit yang bisa kamu pakai. <br>MAIN DENGAN TEMAN, KELUARGA, DAN MUSUH<br>Buat ruang Pertarungan multipemain sendiri! Tantang temanmu dan tentukan skor berdasarkan formasi Skuad terbaik - yang mampu bertahan dalam Pertarungan dan menjadi Skuad terkuat!<br>Kebijakan Privasi:<br>http://supercell.com/en/privacy-policy/<br>Ketentuan Layanan:<br>http://supercell.com/en/terms-of-service/<br>Panduan Orang Tua:<br>http://supercell.com/en/parents/"
}