{
  "images": [
    "https://play-lh.googleusercontent.com/_lA0oRLBaETnv0Nd9p2FxFp9EW-oV_x4SGcWcOLGr8zstYLl1kS48mqRWqa1j4gkOAk=w526-h296-rw",
    "https://play-lh.googleusercontent.com/826MP_xHDVgbGkXMIumDM2_KyGrD6SmH_OpZtpkiHl328EsmFPrHd2Z-zl5xruQhhA=w526-h296-rw",
    "https://play-lh.googleusercontent.com/RLx_YL5L39ptE2nXdsL-iok_em7ewveQv3CaAOjQN8V1iSmbJJsKlLtucF6B4DX371ij=w526-h296-rw",
    "https://play-lh.googleusercontent.com/IPa2ytf-QOFfL5fyxSxOUiCLZcVeD1KFhSiOZ42mKGdoCOzINXDJ9FQk2bl_mQ54xDZn=w526-h296-rw",
    "https://play-lh.googleusercontent.com/Y4FBJszwebnbslrwD5sPKd-_SmxWgQzcpvYapz5adH_N3zbkpQ8tcr6a_cP7ogBo7Q=w526-h296-rw"
  ],
  "title": "Shining Nikki-Fashion Makeover",
  "icon": "https://play-lh.googleusercontent.com/rYJ-_YrcDfQ4jB7SEjirnARzyVyIYvjoK0v6Zis9xo2izD6Un6JmRiPUcETIiNEPWw=w240-h480-rw",
  "subTitle": "Simulation/Lifestyle/Dress-up",
  "desc": "Shining Nikki เป็นเกม RPG แต่งตัว 3D แบบ free-to-play พัฒนาโดย Papergames และเป็นภาคที่สี่ของซีรีส์ Nikki เปิดตัวทั่วโลกเมื่อวันที่ 5 กรกฎาคม 2021 เชิญผู้เล่นเข้าสู่โลกมหัศจรรย์ Miraland ที่ซึ่งความงามและแฟชั่นคือกุญแจสำคัญในการช่วยโลก<br><br>กราฟิกและประสบการณ์ 3D<br>ต่อยอดจาก Love Nikki: Dress Up Queen เกมนี้นำเสนอ สภาพแวดล้อม 3D เต็มรูปแบบ มอบประสบการณ์ที่ดื่มด่ำและสวยงามกว่าเดิม แต่ละโมเดลมี มากกว่า 80,000 โพลิกอน, พื้นผิวผ้าเสมือนจริง และระบบแสงที่ซับซ้อน ทำให้ประสบการณ์แต่งตัวสมจริงและมีชีวิตชีวา<br><br>การแสดงออกผ่านแฟชั่น<br>แก่นของ Shining Nikki คือ การแสดงออกผ่านแฟชั่น ผู้เล่นสามารถสะสม ชุดกว่า 1,000 ชุด แต่ละชุดสะท้อนประวัติศาสตร์และวัฒนธรรมอันหลากหลายของ Miraland เกมมี ระบบตู้เสื้อผ้าที่แข็งแกร่ง ทำให้สามารถสร้างการผสมผสานและสไตล์ได้ไม่จำกัด ตั้งแต่ชุดลำลองไปจนถึงชุดราตรียาวหรู<br><br>เนื้อเรื่อง<br>เนื้อเรื่องดำเนินผ่านหลายบท ผู้เล่นร่วมกับ Nikki ในการค้นหาความลับของ Miraland เรื่องราวเจาะลึก ความทรงจำ, อัตลักษณ์, และพลังแห่งความงาม แต่ละบทนำตัวละครใหม่และความท้าทาย เมื่อผู้เล่นก้าวหน้า สามารถสร้างความสัมพันธ์กับ Nikki และตัวละครอื่น ๆ ปลดล็อกเนื้อเรื่องลึกและเข้าถึงชุดและความสามารถพิเศษ<br><br>การต่อสู้แฟชั่น<br>การต่อสู้แฟชั่นเป็น องค์ประกอบหลักของเกม ผู้เล่นเข้าร่วมการแข่งขันสไตลิ่ง ต้องสร้างชุดที่ตรงกับธีมและเกณฑ์ที่กำหนด ความสำเร็จต้องอาศัยความเข้าใจกลไกเกม เช่น การจับคู่คุณสมบัติและการเลือกชุดเชิงกลยุทธ์ การชนะการแข่งขันมอบ ชุดใหม่, ทรัพยากร, และความก้าวหน้าในเนื้อเรื่อง<br><br>ชุมชนและกิจกรรม<br>Shining Nikki ส่งเสริม ความรู้สึกชุมชน ผ่านระบบกิลด์และกิจกรรมร่วมมือ ผู้เล่นสามารถเข้าร่วมกิลด์เพื่อทำกิจกรรมกลุ่ม, แบ่งปันทรัพยากร และสนับสนุนกันและกันในความท้าทาย เกมมี กิจกรรมตามฤดูกาลและชุดจำกัด เพื่อให้เนื้อหาใหม่และน่าสนใจ กิจกรรมเหล่านี้มักร่วมมือกับแฟรนไชส์ยอดนิยม นำตัวละครและธีมที่เป็นที่รักเข้าสู่โลก Miraland"
}