{
  "images": [
    "https://play-lh.googleusercontent.com/lbhdGQb7vNrdgKB-VMKxOZJcNrMt_NsiqC7d0apEx3vk-BzP_7pcWQmis1EIyYuXzuk=w526-h296-rw",
    "https://play-lh.googleusercontent.com/sMsjGo7iQAuQ7hHLh_oUUPvPnkD4kHMDS2JWSpFbj5lFKF4HF2uomgXH_F9wlLpezss=w526-h296-rw",
    "https://play-lh.googleusercontent.com/aFwZfnER4t1toBiLmQq6WdcsRaQ1dkQQ-na9_wemrE_2rTIcDTU3v5Psd40Cn-DQNtZP=w526-h296-rw",
    "https://play-lh.googleusercontent.com/M8dMmMudqSm688G0Ugww4k5msOkoX7DmjkqPtuyi8LnjHJPWG1EssVs5-czjSTPvDA=w526-h296-rw",
    "https://play-lh.googleusercontent.com/PZY2FoUMbrf_bvKoX3f68QuJ1I6UdjV7CGUe9pTZA5b7Ddf09HeXj_YjxkDf5WQ6u9o=w526-h296-rw"
  ],
  "title": "Disney Twisted-Wonderland",
  "icon": "https://play-lh.googleusercontent.com/38aepJhV1nRpNm0FEkS_RHPETxfVxs3dZiUXGXCIsE1c-4J8Po-7eRAOEWmyUmHW6Mc=w240-h480-rw",
  "subTitle": "RPG/RPG แบบผลัดกันเล่น/เล่นฆ่าเวลา",
  "desc": "[ประกาศสำคัญ] <br>・กำหนดวันเปิดตัวคือวันที่ 20 มกราคม<br>・เนื้อหาเป็นภาษาอังกฤษพร้อมคำบรรยายภาษาญี่ปุ่น<br>ตัวละครที่ได้รับแรงบันดาลใจจากตัวร้ายของดิสนีย์สร้างแผนการชั่วร้ายในสนามโรงเรียนในเกมผจญภัยสุดมหัศจรรย์ที่ประกอบด้วยเกมจังหวะและการต่อสู้สไตล์ RPG!<br>■คอนเซ็ปต์ เรื่องราวหลัก และการออกแบบตัวละครโดย Yana Toboso (ผู้สร้าง \"Black Butler\")<br>เรื่องย่อ<br>บางที \"ตัวร้าย\" อาจมีอะไรมากกว่าที่เห็นก็ได้...<br>คุณถูกเรียกตัวโดยกระจกวิเศษสู่ Twisted Wonderland โลกที่แตกต่างจากโลกของคุณโดยสิ้นเชิง และมาถึง Night Raven College ซึ่งเป็นโรงเรียนเวทมนตร์อันทรงเกียรติ<br>เมื่อไม่มีที่อื่นให้ไป คุณจึงยอมรับการต้อนรับของอาจารย์ใหญ่ที่สวมหน้ากากและเริ่มมองหาทางกลับบ้าน<br>คุณพบในไม่ช้าว่านักเรียนของโรงเรียนนี้มีความสามารถไม่แพ้กับที่พวกเขามีปัญหา—การทะเลาะเบาะแว้งและการแข่งขันเป็นสิ่งที่ไม่มีวันสิ้นสุด<br>คุณจะสามารถทำงานร่วมกับพวกเขาและกลับมาจากที่ที่คุณมาได้หรือไม่?<br> และความลับใดที่ซ่อนอยู่ในใจอันชั่วร้ายของนักเรียนเหล่านี้?<br>■เพลิดเพลินไปกับการต่อสู้แบบผลัดตาและเกมจังหวะที่เรียบง่าย!<br>ภาพรวมของเกม<br>คุณจะได้เรียนวิชาประวัติศาสตร์เวทมนตร์ การเล่นแร่แปรธาตุ และการบินควบคู่ไปกับนักเรียนของ Night Raven College<br>เมื่อคุณศึกษาลึกลงไปในเนื้อหามากขึ้น คุณจะปลดล็อกเนื้อเรื่องเพิ่มเติม ซึ่งรูปแบบการเล่นแบ่งออกเป็นสามส่วน:<br>—ส่วนของเนื้อเรื่อง ซึ่งคุณจะได้ดำเนินเรื่องผ่านเรื่องราวของ Twisted Wonderland<br>—การต่อสู้ ซึ่งตัวละครต่อสู้กันโดยใช้คาถา<br>—Twistunes ซึ่งคุณจะได้เล่นเกมจังหวะและเคาะตามจังหวะเพลง<br>ละครที่มืดหม่นและน่าหลงใหลกำลังรอคุณอยู่<br>■มีตัวละครและหอพักที่ได้รับแรงบันดาลใจจากภาพยนตร์คลาสสิกของดิสนีย์! Night Raven College มีหอพัก 7 แห่ง ซึ่งแต่ละแห่งเป็นบ้านของตัวละครที่มีเอกลักษณ์เฉพาะตัว:<br>หอพัก Heartslabyul—Twisted จากเรื่อง Alice in Wonderland<br>หอพัก Savanaclaw—Twisted จากเรื่อง The Lion King<br>หอพัก Octavinelle—Twisted จากเรื่อง The Little Mermaid<br>หอพัก Scarabia—Twisted จากเรื่อง Aladdin<br>หอพัก Pomefiore—Twisted จากเรื่อง Snow White and the Seven Dwarfs<br>หอพัก Ignihyde—Twisted จากเรื่อง Hercules<br>หอพัก Diasomnia—Twisted จากเรื่อง Sleeping Beauty<br>เจ้าหน้าที่<br>แนวคิด เรื่องราวหลัก และการออกแบบตัวละคร: Yana Toboso<br>สนับสนุนโดย SQUARE ENIX<br>การพัฒนาและการจัดการ: f4samurai<br>การออกแบบโลโก้ ส่วนต่อประสานผู้ใช้ สัญลักษณ์ และไอคอน: Wataru Osakabe<br>พื้นหลัง: Atelier Musa<br>การวางแผนและการจัดจำหน่าย: Aniplex<br>ดนตรี: Takumi Ozawa<br>แอนิเมชั่นเปิดเรื่อง: TROYCA<br>การผลิตเสียง: HALF H-P สตูดิโอ<br>ระบบปฏิบัติการที่รองรับ: <br>ต้องใช้ Android 7.0 ขึ้นไป (ไม่รองรับบางอุปกรณ์)<br>*อาจไม่เสถียรแม้ในอุปกรณ์ที่รองรับ ขึ้นอยู่กับการใช้งาน"
}