{
  "images": [
    "https://play-lh.googleusercontent.com/wZB6aZQDglCe9oClsSWrTpJBsLgjnn9hv1sncFXlJeB9yfxGnFGSK06dbTDYnVTC5w=w526-h296-rw",
    "https://play-lh.googleusercontent.com/2I6SbUQaoOZ-atbRO2w86TWrV329R2AqRLsT6hFVFFJkDBDPDpmWF0wbkXHvvYTHkL8=w526-h296-rw",
    "https://play-lh.googleusercontent.com/iuUgQZvtT7r9hEF7S5AX-I5nF0OaErzh4rSVuTdd0wiw8sFbtUn2WyY9g2B0qfmuYpeb=w526-h296-rw",
    "https://play-lh.googleusercontent.com/H1lLwQgkRs3e4sP1P7Txdnk5BG5sxfb2_Sf0FfBOmcJ8uPOZtHTrxa6E7trrn3iUqDY=w526-h296-rw",
    "https://play-lh.googleusercontent.com/8eLI7mG-5i0LJcAsZApemJ86iorVJwnHhQdDFdqZo19o1SXZI6Tx-5I4_kUOxe6X4SM=w526-h296-rw"
  ],
  "title": "Plants vs. Zombies™",
  "icon": "https://play-lh.googleusercontent.com/hO7716hh7NCcFauJedDclX-R3Zh9JmbSs8AUU6TP2edGVILlZM7gmyt_8WPCZELiPQA=w240-h480-rw",
  "subTitle": "Strategiczne/Obrona wieży",
  "desc": "Przygotuj się na zabrudzanie roślin, ponieważ tłum uwielbiających zabawę zombie zamierza wtargnąć do twojego domu. Użyj swojego arsenału 49 roślin zabijających zombie — strzelby grochowe, orzechy ścienne, wiśnie i inne — aby rozdrobnić 26 rodzajów zombie, zanim wyważą twoje drzwi. <br>Ta aplikacja oferuje zakupy w aplikacji. Możesz wyłączyć zakupy w aplikacji, korzystając z ustawień urządzenia<br>ZWYCIĘZCA PONAD 30 NAGRÓD GRY ROKU*<br>50 NIEZABAWNYCH POZIOMÓW<br>Pokonaj wszystkie 50 poziomów trybu Przygody — w dzień, w nocy, we mgle, w basenie, na dachu i nie tylko. Dodatkowo odpieraj nieustającą falę zombie tak długo, jak potrafisz, w trybie Przetrwania!<br>NIE OGRODOWE GHOULE<br>Walcz z zombie skoczkami o tyczce, nurkami, łyżwiarzami i 26 innymi niezabawnymi zombie. Każdy z nich ma swoje własne specjalne umiejętności, więc musisz szybko myśleć i sadzić szybciej, aby z nimi wszystkimi walczyć.<br>Wymaga akceptacji Polityki prywatności i plików cookie EA oraz Umowy użytkownika.<br>MĄDRZEJSZY NIŻ PRZECIĘTNY ZOMBIE<br>Uważaj, jak wykorzystujesz swoje ograniczone zapasy zieleniny i nasion. Zombie tak bardzo kochają mózgi, że będą skakać, biegać, tańczyć, pływać, a nawet zjadać rośliny, aby dostać się do twojego domu. Otwórz Almanach, aby dowiedzieć się więcej o wszystkich zombie i roślinach, co pomoże ci zaplanować strategię.<br>WALCZ DŁUŻEJ, STAŃ SIĘ SILNIEJSZY<br>Zdobądź 49 potężnych roślin wieloletnich w miarę postępów i zbieraj monety, aby kupić ślimaka, ulepszenia i wiele więcej.<br>ROZWIJAJ SIĘ Z GRĄ<br>Pokaż swoje umiejętności w zabijaniu zombie, zdobywając 46 niesamowitych osiągnięć i pokaż swoje umiejętności w zabijaniu zombie.<br>PAKIETY MONET<br>Potrzebujesz monet na świetne nowe rzeczy? Kup do 600 000 monet bezpośrednio z Menu głównego.<br> *Oryginalna gra do pobrania na Mac/PC.<br>Bądź pierwszy, który się dowie! Uzyskaj informacje od EA na temat świetnych ofert, a także najnowsze aktualizacje gier, wskazówki i nie tylko…<br>ODWIEDŹ NAS: eamobile.com<br>OBSERWUJ NAS: twitter.com/eamobile<br>POLUB NAS: facebook.com/eamobile<br>OBEJRZYJ NAS: youtube.com/eamobilegames<br>Umowa użytkownika: terms.ea.com<br>Odwiedź https://help.ea.com/, aby uzyskać pomoc lub zadać pytania.<br>EA może wycofać funkcje i usługi online po 30 dniach od powiadomienia opublikowanego na stronie www.ea.com/1/service-updates.<br>Ważne informacje dla konsumentów. Ta aplikacja zawiera bezpośrednie linki do Internetu<br>Wymaga akceptacji Polityki prywatności i plików cookie EA oraz Umowy użytkownika"
}