{
  "images": [
    "https://play-lh.googleusercontent.com/gcXSOIzW6nOJLfBE1SQvGTkvi3DCjE8yYwVpscre2QOwrjVH7WTJNhyw6bVD0UZgIaI=w526-h296-rw",
    "https://play-lh.googleusercontent.com/QJkBk6kqbxUdMAMSPfg-dTw0crdwmbjC7eTngWGl8koWMOa-ymWxBr34DIKmimtjrFVV=w526-h296-rw",
    "https://play-lh.googleusercontent.com/ZuKywp92MKeCB6yyaiFAZCh-n0qgvk7ukXg40QZ7Ra4JYManVn_L1i45dz9PZ1US3A=w526-h296-rw",
    "https://play-lh.googleusercontent.com/O65ZR5Otoijyd_2dsT8PMNHTARGZH9bvn6v5tIaCXMV9j8brau3-wlZrknh0LcaSnQ=w526-h296-rw",
    "https://play-lh.googleusercontent.com/ioOTiHmLzg3V3nWUeLVPfP-FTqAm5iFxmOKy5Onwf8g4iFI0OCiWlBUq2Ez0fV9M4_Y9=w526-h296-rw"
  ],
  "title": "Tears of Themis",
  "icon": "https://play-lh.googleusercontent.com/oFdZQzPmxdYqTUWdokShvvTem2UIdTBmRViB1yyy6grCZTxS8JrmwV6W5KnL5ThkAxD8jZcztD7bekM41VoR=w240-h480-rw",
  "subTitle": "Avventura/Storie interattive/Casual",
  "desc": "Quelli che sembravano casi indipendenti cominciano lentamente a collegarsi e a formare un quadro più ampio.<br>La mano dietro a tutto ciò non ha riguardo per l'ordine sociale e mira solo a distruggere tutto ciò che è dignitoso e buono.<br>Man mano che la verità diventa più oscura e avvolta nel mistero, i confini tra il bene e il male si confondono. Con il mondo contro di te e le parole della ragione che cadono nel vuoto...<br>Sarai ancora determinato a sostenere le tue scelte e le tue convinzioni?<br>◆ Raccolta di prove: perlustra la scena e scopri la verità<br>Scopri prove delicate e oggetti che giacciono sulla scena del crimine e rivela la verità.<br>Acquisire testimonianze dai sospetti. Analizza e confronta le loro testimonianze con indizi contraddittori trovati su di loro per scoprire le prove chiave.<br>Sconfiggi i tuoi avversari in tribunale con logica e ingegno per offrire la vera giustizia!<br>◆ Squisite illustrazioni dinamiche: scopri tutto su di lui<br>Le squisite illustrazioni dinamiche danno vita alle carte, incorniciando per sempre il tuo prezioso ricordo con lui con dettagli vividi.<br>Una volta sbloccata una storia personale, inizierai a ricevere videochiamate dalla tua persona speciale! Concediti la sua voce risonante e le interazioni quotidiane!<br>Vai ad appuntamenti che ti faranno sciogliere e vivere momenti intimi da batticuore.<br>◆ Ricordi preziosi: crea insieme ricordi preziosi<br>Ogni personaggio ha i suoi archi narrativi unici che nascondono i suoi segreti più ben custoditi.<br>Avventurati più a fondo nel suo cuore completando queste storie per conoscere la verità su di lui, creando ricordi che appartengono solo a voi due.<br>◆Salotto personale: uno spazio privato per te e per loro<br>La nuova funzionalità Lounge è ora disponibile. Raccogli progetti e costruisci mobili per arredare lo spazio dolce in cui trascorri giornate piacevoli con loro.<br>Sito ufficiale: https://tot.hoyoverse.com/en-us/<br>Account Twitter ufficiale: https://twitter.com/TearsofThemisEN<br>Fanpage ufficiale di Facebook: https://www.facebook.com/tearsofthemis.glb<br>Servizio clienti: totcs_glb@hoyoverse.com"
}